LICENSE
MANIFEST.in
README.md
VERSION
requirements.txt
setup.py
countergenedit/__init__.py
countergenedit.egg-info/PKG-INFO
countergenedit.egg-info/SOURCES.txt
countergenedit.egg-info/dependency_links.txt
countergenedit.egg-info/requires.txt
countergenedit.egg-info/top_level.txt
countergenedit/editing/__init__.py
countergenedit/editing/activation_ds.py
countergenedit/editing/activation_utils.py
countergenedit/editing/direction_algos.py
countergenedit/editing/edition.py
countergenedit/editing/models.py
countergenedit/evaluation/__init__.py
countergenedit/evaluation/classification_models.py
countergenedit/evaluation/generative_models.py
countergenedit/tools/__init__.py
countergenedit/tools/math_utils.py
countergenedit/tools/utils.py